odoo/addons/so_report_only_date/README.rst
odoo/addons/so_report_only_date/__init__.py
odoo/addons/so_report_only_date/__manifest__.py
odoo/addons/so_report_only_date/report/sale_report_templates.xml
odoo/addons/so_report_only_date/static/description/icon.png
odoo_addon_so_report_only_date-15.0.1.0.1.2.dist-info/METADATA
odoo_addon_so_report_only_date-15.0.1.0.1.2.dist-info/WHEEL
odoo_addon_so_report_only_date-15.0.1.0.1.2.dist-info/top_level.txt
odoo_addon_so_report_only_date-15.0.1.0.1.2.dist-info/RECORD
